mine/__init__.py
mine/cli.py
mine/common.py
mine/daemon.py
mine/manager.py
mine/models/__init__.py
mine/models/application.py
mine/models/computer.py
mine/models/config.py
mine/models/data.py
mine/models/status.py
mine/models/timestamp.py
mine/services.py
mine/settings.py
mine/tests/__init__.py
mine/tests/conftest.py
mine/tests/files/.gitignore
mine/tests/files/mine-in.yml
mine/tests/files/mine-out.yml
mine/tests/test_cli.py
mine/tests/test_manager.py
mine/tests/test_models_application.py
mine/tests/test_models_computer.py
mine/tests/test_models_config.py
mine/tests/test_models_data.py
mine/tests/test_models_status.py
mine/tests/test_models_timestamp.py
mine/tests/test_services.py
mine-4.2.3.dist-info/LICENSE.md
mine-4.2.3.dist-info/METADATA
mine-4.2.3.dist-info/WHEEL
mine-4.2.3.dist-info/entry_points.txt
mine-4.2.3.dist-info/RECORD
