Metadata-Version: 2.1
Name: mine
Version: 4.2.3
Summary: Share application state across computers using Dropbox.
Home-page: https://pypi.org/project/mine
License: MIT
Author: Jace Browning
Author-email: jacebrowning@gmail.com
Requires-Python: >=3.10,<4.0
Classifier: Development Status :: 5 - Production/Stable
Classifier: Environment :: Console
Classifier: Intended Audience :: End Users/Desktop
Classifier: License :: OSI Approved :: MIT License
Classifier: Natural Language :: English
Classifier: Operating System :: OS Independent
Classifier: Programming Language :: Python
Classifier: Programming Language :: Python :: 3
Classifier: Programming Language :: Python :: 3.10
Classifier: Programming Language :: Python :: 3.11
Classifier: Programming Language :: Python :: 3.12
Classifier: Topic :: System
Classifier: Topic :: System :: Monitoring
Classifier: Topic :: Utilities
Requires-Dist: crayons (>=0.4,<0.5)
Requires-Dist: datafiles (>=2.1,<3.0)
Requires-Dist: minilog (>=2.1,<3.0)
Requires-Dist: psutil (>=5.6,<5.7)
Requires-Dist: universal-startfile (>=0.2,<0.3)
Project-URL: Documentation, https://mine.readthedocs.io
Project-URL: Repository, https://github.com/jacebrowning/mine
